odoo/addons/stock_request_direction/README.rst
odoo/addons/stock_request_direction/__init__.py
odoo/addons/stock_request_direction/__manifest__.py
odoo/addons/stock_request_direction/i18n/es.po
odoo/addons/stock_request_direction/i18n/it.po
odoo/addons/stock_request_direction/i18n/stock_request_direction.pot
odoo/addons/stock_request_direction/i18n/zh_CN.po
odoo/addons/stock_request_direction/models/__init__.py
odoo/addons/stock_request_direction/models/stock_request.py
odoo/addons/stock_request_direction/models/stock_request_order.py
odoo/addons/stock_request_direction/readme/CONTRIBUTORS.rst
odoo/addons/stock_request_direction/readme/DESCRIPTION.rst
odoo/addons/stock_request_direction/readme/USAGE.rst
odoo/addons/stock_request_direction/static/description/icon.png
odoo/addons/stock_request_direction/static/description/index.html
odoo/addons/stock_request_direction/tests/__init__.py
odoo/addons/stock_request_direction/tests/test_stock_request_direction.py
odoo/addons/stock_request_direction/views/res_config_settings.xml
odoo/addons/stock_request_direction/views/stock_request_order_views.xml
odoo/addons/stock_request_direction/views/stock_request_views.xml
odoo14_addon_stock_request_direction-14.0.1.0.2.dev6.dist-info/METADATA
odoo14_addon_stock_request_direction-14.0.1.0.2.dev6.dist-info/WHEEL
odoo14_addon_stock_request_direction-14.0.1.0.2.dev6.dist-info/top_level.txt
odoo14_addon_stock_request_direction-14.0.1.0.2.dev6.dist-info/RECORD
